exordium/__init__.py
exordium/admin.py
exordium/apps.py
exordium/dynamic_preferences_registry.py
exordium/models.py
exordium/tables.py
exordium/tests.py
exordium/urls.py
exordium/views.py
exordium/fixtures/initial_data.json
exordium/management/__init__.py
exordium/management/commands/__init__.py
exordium/management/commands/importmysqlampachedates.py
exordium/migrations/0001_initial.py
exordium/migrations/0002_add_m4a_support.py
exordium/migrations/0003_add_opus_support.py
exordium/migrations/0004_media_url_split.py
exordium/migrations/__init__.py
exordium/static/exordium/download.png
exordium/static/exordium/favicon.png
exordium/static/exordium/favicon.xcf
exordium/static/exordium/no_album_art.png
exordium/static/exordium/no_album_art.xcf
exordium/static/exordium/no_album_art_small.png
exordium/static/exordium/no_play.png
exordium/static/exordium/play.png
exordium/static/exordium/style.css
exordium/static/exordium/jplayer/popup.html
exordium/static/exordium/jplayer/js/jplayer.playlist.min.js
exordium/static/exordium/jplayer/js/jquery.jplayer.min.js
exordium/static/exordium/jplayer/js/jquery.min.js
exordium/static/exordium/jplayer/skin/pink.flag.600px/README-600px.txt
exordium/static/exordium/jplayer/skin/pink.flag.600px/css/jplayer.pink.flag.min.css
exordium/static/exordium/jplayer/skin/pink.flag.600px/image/jplayer.pink.flag.jpg
exordium/static/exordium/jplayer/skin/pink.flag.600px/image/jplayer.pink.flag.seeking.gif
exordium/static/exordium/jplayer/skin/pink.flag.600px/image/jplayer.pink.flag.video.play.png
exordium/templates/exordium/.album.html.swp
exordium/templates/exordium/album.html
exordium/templates/exordium/album_artist_column.html
exordium/templates/exordium/album_download.html
exordium/templates/exordium/album_image_list.html
exordium/templates/exordium/album_info.html
exordium/templates/exordium/album_stream.m3u
exordium/templates/exordium/artist.html
exordium/templates/exordium/base.html
exordium/templates/exordium/browse.html
django_exordium-1.4.3.dist-info/LICENSE-jPlayer.txt
django_exordium-1.4.3.dist-info/LICENSE-jQuery.txt
django_exordium-1.4.3.dist-info/LICENSE.txt
django_exordium-1.4.3.dist-info/METADATA
django_exordium-1.4.3.dist-info/WHEEL
django_exordium-1.4.3.dist-info/top_level.txt
django_exordium-1.4.3.dist-info/RECORD
