Metadata-Version: 2.1
Name: django-exordium
Version: 1.4.3
Summary: A Django-based readonly web music library application.
Home-page: https://apocalyptech.com/exordium/
Author: CJ Kucera
Author-email: pez@apocalyptech.com
License: BSD License
Platform: UNKNOWN
Classifier: Development Status :: 5 - Production/Stable
Classifier: Environment :: Web Environment
Classifier: Framework :: Django
Classifier: Framework :: Django :: 4.0
Classifier: Intended Audience :: End Users/Desktop
Classifier: License :: OSI Approved :: BSD License
Classifier: Natural Language :: English
Classifier: Operating System :: OS Independent
Classifier: Programming Language :: Python
Classifier: Programming Language :: Python :: 3
Classifier: Programming Language :: Python :: 3.8
Classifier: Programming Language :: Python :: 3.9
Classifier: Programming Language :: Python :: 3.10
Classifier: Programming Language :: Python :: 3 :: Only
Classifier: Topic :: Internet :: WWW/HTTP
Classifier: Topic :: Internet :: WWW/HTTP :: Dynamic Content
Classifier: Topic :: Multimedia :: Sound/Audio
Requires-Dist: Django (~=4.0)
Requires-Dist: mutagen (~=1.45)
Requires-Dist: Pillow (~=9.0)
Requires-Dist: django-tables2 (~=2.4)
Requires-Dist: django-dynamic-preferences (~=1.11)
